{
  "publicPath": "/_nuxt/",
  "all": [
    "../server/index.spa.html",
    "../server/index.ssr.html",
    "021e874.js",
    "2a4ba4c.js",
    "52b5851.js",
    "5a201aa.js",
    "65eafb9.js",
    "7593732.js",
    "88b435f.js",
    "895df73.js",
    "9cd0877.js",
    "LICENSES",
    "b161ecf.js",
    "ce176b1.js",
    "f4e0494.js"
  ],
  "initial": [
    "7593732.js",
    "b161ecf.js",
    "895df73.js",
    "65eafb9.js"
  ],
  "async": [
    "021e874.js",
    "2a4ba4c.js",
    "52b5851.js",
    "5a201aa.js",
    "88b435f.js",
    "9cd0877.js",
    "ce176b1.js",
    "f4e0494.js"
  ],
  "modules": {
    "29119337": [
      12
    ],
    "56011889": [
      12
    ],
    "71326559": [
      12
    ],
    "77556014": [
      12
    ],
    "79909320": [
      12
    ],
    "86365952": [
      3
    ],
    "89af49ac": [
      6
    ],
    "5041ca24": [
      12
    ],
    "e57f9ed6": [
      12
    ],
    "510f54ce": [
      9
    ],
    "17f25615": [
      12
    ],
    "2b1f3d86": [
      12
    ],
    "25de7aa0": [
      12
    ],
    "26dfe4cb": [
      12
    ],
    "0d20ff3a": [
      12
    ],
    "3960709f": [
      12
    ],
    "d8080bca": [
      12
    ],
    "7b3d86e8": [
      12
    ],
    "3df6fed2": [
      12
    ],
    "d367792e": [
      6
    ],
    "6d7a270a": [
      6
    ],
    "3b84dc23": [
      6
    ],
    "7cb5f086": [
      6
    ],
    "5f0ac3d2": [
      6
    ],
    "4e0238da": [
      6
    ],
    "141d760c": [
      6
    ],
    "4467a0a7": [
      6
    ],
    "8536ed12": [
      6
    ],
    "799c90ce": [
      6
    ],
    "512bf66c": [
      6
    ],
    "62d909b1": [
      6
    ],
    "fbac0fb2": [
      6
    ],
    "56c760c9": [
      6
    ],
    "d2dce54e": [
      6
    ],
    "38404df8": [
      6
    ],
    "0e628888": [
      6
    ],
    "8ac844b6": [
      6
    ],
    "6e0a5490": [
      6
    ],
    "00b2ab0a": [
      12
    ],
    "05b91410": [
      12
    ],
    "3b935ce4": [
      12
    ],
    "dc6d7c48": [
      12
    ],
    "175b1998": [
      12
    ],
    "731a943a": [
      12
    ],
    "a6ef25dc": [
      12
    ],
    "8aad0f26": [
      9
    ],
    "5413bf3e": [
      9
    ],
    "366b7634": [
      9
    ],
    "e0042044": [
      9
    ],
    "e95b1234": [
      9
    ],
    "29ea71e7": [
      9
    ],
    "4af7412c": [
      12
    ],
    "476a5092": [
      12
    ],
    "4991d3fd": [
      12
    ],
    "6b51b95a": [
      12
    ],
    "20aaf02a": [
      12
    ],
    "1619ee1e": [
      12
    ],
    "6ba05d8d": [
      12
    ],
    "3f064ee3": [
      12
    ],
    "303bbc91": [
      12
    ],
    "443ad00c": [
      12
    ],
    "3369bee4": [
      9
    ],
    "7005633a": [
      9
    ],
    "3258e298": [
      12
    ],
    "5cbbc114": [
      12
    ],
    "2bb38be9": [
      12
    ],
    "0a2cebf9": [
      12
    ],
    "ec990278": [
      12
    ],
    "71d62cab": [
      12
    ],
    "1fac3664": [
      12
    ],
    "a9a2ed08": [
      12
    ],
    "7b515c60": [
      12
    ],
    "8a8b7922": [
      12
    ],
    "6f6dea80": [
      12
    ],
    "250adc84": [
      12
    ],
    "6119787c": [
      12
    ],
    "2d024640": [
      12
    ],
    "98a5c996": [
      12
    ],
    "127f29f6": [
      12
    ],
    "b06f0822": [
      12
    ],
    "2cfdba8a": [
      12
    ],
    "1bee9ee5": [
      12
    ],
    "7157c1ed": [
      12
    ],
    "93dbebc0": [
      12
    ],
    "4e759646": [
      12
    ],
    "28811e65": [
      9
    ],
    "230b9fde": [
      9
    ],
    "a84a6fc0": [
      6
    ],
    "3d6d7f25": [
      12
    ],
    "68df367d": [
      6
    ],
    "17856b45": [
      12
    ],
    "2d0b5dac": [
      12
    ],
    "7066221a": [
      12
    ],
    "60d387e3": [
      12
    ],
    "5471458a": [
      12
    ],
    "bd1fe5c2": [
      12
    ],
    "40e35150": [
      12
    ],
    "1155cf97": [
      12
    ],
    "6e1f29e7": [
      12
    ],
    "d6498670": [
      12
    ],
    "fb247680": [
      12
    ],
    "41e9458b": [
      12
    ],
    "15f73621": [
      6
    ],
    "565c86cc": [
      9
    ],
    "1390954a": [
      12
    ],
    "6a29a071": [
      12
    ],
    "5ce95241": [
      12
    ],
    "7e29f6e3": [
      12
    ],
    "7763cb12": [
      12
    ],
    "05b714ac": [
      12
    ],
    "456cb89b": [
      12
    ],
    "106ac6ef": [
      12
    ],
    "0577a281": [
      12
    ],
    "6076e836": [
      12
    ],
    "254adf64": [
      12
    ],
    "2dada8db": [
      12
    ],
    "58108a1c": [
      12
    ],
    "5e2ce185": [
      12
    ],
    "7ae0e004": [
      12
    ],
    "024293f1": [
      12
    ],
    "82c23de8": [
      12
    ],
    "6b1d92d5": [
      12
    ],
    "40ad3a03": [
      12
    ],
    "702e4c1a": [
      12
    ],
    "747e48ba": [
      12
    ],
    "7da5fc3a": [
      12
    ],
    "ede4c95c": [
      12
    ],
    "db1e9538": [
      12
    ],
    "ea2eed78": [
      9
    ],
    "c438b4e4": [
      6
    ],
    "0e415be0": [
      9
    ],
    "248e695a": [
      6
    ],
    "58a8cd04": [
      12
    ],
    "49582d1a": [
      12
    ],
    "0abd93b6": [
      12
    ],
    "4df0bb20": [
      12
    ],
    "2bb41248": [
      12
    ],
    "fcb7f8ba": [
      12
    ],
    "3a2881b5": [
      12
    ],
    "1cf2b660": [
      12
    ],
    "ba422344": [
      9
    ],
    "c69a36f2": [
      9
    ],
    "702c17eb": [
      9
    ],
    "22fb96dc": [
      12
    ],
    "5cabe32e": [
      9
    ],
    "135d8c93": [
      12
    ],
    "76bc272d": [
      9
    ],
    "57a808d2": [
      6
    ],
    "08fe6d12": [
      12
    ],
    "47bc2965": [
      6
    ],
    "6f82931f": [
      12
    ],
    "1c1f3970": [
      6
    ],
    "0afa2e8c": [
      12
    ],
    "00a23b56": [
      12
    ],
    "d5fd25f4": [
      12
    ],
    "1cca3d78": [
      12
    ],
    "d1c5387e": [
      12
    ],
    "33da3de8": [
      12
    ],
    "50bbd5ad": [
      12
    ],
    "2a5975ba": [
      12
    ],
    "c78bc7bc": [
      12
    ],
    "022e39af": [
      12
    ],
    "73e69753": [
      12
    ],
    "a03d5134": [
      12
    ],
    "638d50b8": [
      12
    ],
    "937c3c82": [
      12
    ],
    "1175127f": [
      12
    ],
    "ab3db37c": [
      12
    ],
    "2191586b": [
      12
    ],
    "b53140da": [
      12
    ],
    "31db92d7": [
      12
    ],
    "8ab52990": [
      12
    ],
    "18efa561": [
      12
    ],
    "4473cc77": [
      12
    ],
    "7b0bf34e": [
      12
    ],
    "2da35cd9": [
      6
    ],
    "3bbb114a": [
      6
    ],
    "4494c33f": [
      12
    ],
    "03070787": [
      12
    ],
    "2e8b2e9d": [
      12
    ],
    "91e2accc": [
      12
    ],
    "549f7d77": [
      12
    ],
    "5e23c6b0": [
      12
    ],
    "63e41fca": [
      12
    ],
    "05819d8f": [
      12
    ],
    "8f5a7bc2": [
      12
    ],
    "0eb0c5ed": [
      12
    ],
    "dda0f03a": [
      12
    ],
    "c90f1a7e": [
      9
    ],
    "f03441d0": [
      9
    ],
    "52974f60": [
      9
    ],
    "22bf920a": [
      9
    ],
    "7e92986a": [
      9
    ],
    "49e76902": [
      9
    ],
    "8cfa769e": [
      12
    ],
    "17fef681": [
      9
    ],
    "dc88ed38": [
      6
    ],
    "602edcdf": [
      6
    ],
    "fc06a0a0": [
      6
    ],
    "fe2ddf2a": [
      6
    ],
    "125210b9": [
      6
    ],
    "45e8d234": [
      12
    ],
    "d0cf910e": [
      12
    ],
    "270fcc77": [
      12
    ],
    "0190868c": [
      12
    ],
    "52db52ce": [
      12
    ],
    "11e49cce": [
      12
    ],
    "2d8f5b98": [
      12
    ],
    "e07d31b6": [
      12
    ],
    "0a97d4b8": [
      12
    ],
    "7cd7086d": [
      12
    ],
    "1d9ddc36": [
      12
    ],
    "5afeb220": [
      12
    ],
    "09f0eca8": [
      12
    ],
    "cf5bc7fc": [
      12
    ],
    "67b15a96": [
      12
    ],
    "1ef78f88": [
      12
    ],
    "a9a58af6": [
      3
    ],
    "53a44ca8": [
      3
    ],
    "7125b0f3": [
      3
    ],
    "01cbfd10": [
      3
    ],
    "73671af6": [
      2
    ],
    "5f62723c": [
      2
    ],
    "74863ed1": [
      3
    ],
    "d1a5340e": [
      3
    ],
    "2f325adc": [
      3
    ],
    "610c44e2": [
      3
    ],
    "a3a68f22": [
      3
    ],
    "313ec16d": [
      3
    ],
    "661d7232": [
      3
    ],
    "49991f5a": [
      2
    ],
    "529bda42": [
      2
    ],
    "6e5e0d42": [
      2
    ],
    "25f410bc": [
      5
    ],
    "377081a0": [
      3
    ],
    "4a4b7397": [
      3
    ],
    "5d28fecc": [
      3
    ],
    "b34f3a96": [
      3
    ],
    "6b295fdd": [
      3
    ],
    "8f235d98": [
      3
    ],
    "96c41560": [
      3
    ],
    "43c10055": [
      3
    ],
    "0c0eae39": [
      3
    ],
    "e8ffb5e4": [
      3
    ],
    "f313905a": [
      3
    ],
    "6d0a2f0e": [
      3
    ],
    "e86fac22": [
      3
    ],
    "514dbd62": [
      3
    ],
    "b2beb7ec": [
      3
    ],
    "c1e7bca6": [
      3
    ],
    "05cb35ad": [
      3
    ],
    "05ecac8a": [
      3
    ],
    "6630ced0": [
      3
    ],
    "747cc8f3": [
      3
    ],
    "8aca62cc": [
      3
    ],
    "d0ce8a72": [
      3
    ],
    "21c01e78": [
      3
    ],
    "16264a5c": [
      3
    ],
    "84bdff3e": [
      3
    ],
    "2e30a78f": [
      3
    ],
    "1d04a3bf": [
      3
    ],
    "a18c3c38": [
      3
    ],
    "df5397e0": [
      3
    ],
    "5bfbedb5": [
      3
    ],
    "4605c5de": [
      3
    ],
    "97f6dbd0": [
      3
    ],
    "7803ca95": [
      3
    ],
    "5754d288": [
      3
    ],
    "3ef30cb2": [
      3
    ],
    "293f9a3e": [
      3
    ],
    "5fb1da50": [
      3
    ],
    "a350e73e": [
      3
    ],
    "0ba3f468": [
      3
    ],
    "0143cecd": [
      3
    ],
    "3afec151": [
      3
    ],
    "0d681274": [
      3
    ],
    "254062e5": [
      3
    ],
    "12270e65": [
      3
    ],
    "29d7c2da": [
      3
    ],
    "e9dfcfaa": [
      3
    ],
    "6a5d7baa": [
      3
    ],
    "038ffe41": [
      3
    ],
    "521d0372": [
      3
    ],
    "95f7303a": [
      3
    ],
    "278b7e8f": [
      3
    ],
    "ed121486": [
      3
    ],
    "fea0206a": [
      3
    ],
    "b1128ea0": [
      3
    ],
    "3058b016": [
      3
    ],
    "102f04e5": [
      3
    ],
    "3fe184b8": [
      14
    ],
    "1d05738a": [
      14
    ],
    "34cc045e": [
      14
    ],
    "6f271f6b": [
      14
    ],
    "5d27d1be": [
      14
    ],
    "345ce7e8": [
      14
    ],
    "61d857cc": [
      14
    ],
    "f374beec": [
      14
    ],
    "1b6587a1": [
      14
    ],
    "0c750c81": [
      14
    ],
    "1cdc9b35": [
      14
    ],
    "487d8dba": [
      14
    ],
    "7f011a4e": [
      14
    ],
    "76afd151": [
      14
    ],
    "dbe32530": [
      14
    ],
    "2cdac679": [
      2
    ],
    "c85a28d8": [
      2
    ],
    "73e1e5b0": [
      2
    ],
    "572b2064": [
      2
    ],
    "79a2885b": [
      2
    ],
    "d6631e50": [
      2
    ],
    "460f506b": [
      5
    ],
    "402bf8ed": [
      5
    ],
    "1a121b04": [
      5
    ],
    "204b43c6": [
      5
    ],
    "9c5a44aa": [
      5
    ],
    "589ef8f1": [
      5
    ],
    "b3a7aff8": [
      10
    ],
    "64d3c194": [
      10
    ],
    "2d576206": [
      10
    ],
    "13b46006": [
      10
    ],
    "05f5c970": [
      10
    ],
    "5ae102bd": [
      8
    ],
    "298809a8": [
      8
    ],
    "78ce3138": [
      8
    ],
    "22cd47fc": [
      8
    ],
    "3dc59117": [
      8
    ],
    "2a053dab": [
      4
    ],
    "bd2d199a": [
      4
    ],
    "e441a784": [
      4
    ],
    "1f134c63": [
      4
    ],
    "056d002b": [
      4
    ],
    "3e072f56": [
      13
    ],
    "14a1e118": [
      13
    ],
    "5288702a": [
      13
    ],
    "5ac021e8": [
      13
    ],
    "19457b44": [
      13
    ]
  },
  "assetsMapping": {
    "bba68bf6": [
      "021e874.js",
      "2a4ba4c.js",
      "52b5851.js",
      "5a201aa.js",
      "88b435f.js",
      "9cd0877.js",
      "ce176b1.js",
      "f4e0494.js"
    ],
    "1a3ae26b": [
      "65eafb9.js"
    ],
    "6fca0322": [
      "7593732.js"
    ],
    "7ea24c87": [
      "895df73.js"
    ],
    "085a35c4": [
      "b161ecf.js"
    ]
  }
}